{
  "odata.metadata": "http://89.76.239.245:8080/test/odata/standard.odata/$metadata#Document_ЗаказПокупателя",
  "value": [
    {
      "Ref_Key": "b94c2d43-8291-11ec-b3ce-00155dd72305",
      "Number": "00000002229",
      "Date": "2022-01-31T14:31:48",
      "АдресДоставки": ",, , , м. Київ, , вул. Берковецька, 6, , , ",
      "Контрагент@navigationLinkUrl": "Document_ЗаказПокупателя(guid'b94c2d43-8291-11ec-b3ce-00155dd72305')/Контрагент",
      "Контрагент": {
        "Description": "АШАН УКРАЇНА ГІПЕРМАРКЕТ ТОВ"
      },
      "DeletionMark": false,
      "Ответственный@navigationLinkUrl": "Document_ЗаказПокупателя(guid'b94c2d43-8291-11ec-b3ce-00155dd72305')/Ответственный",
      "Ответственный": {
        "Code": "Крамаренко Леся                                   "
      },
      "ДатаОтгрузки": "2022-02-07T00:00:00"
    },
    {
      "Ref_Key": "abaa9b64-84ca-11ec-b3ce-00155dd72305",
      "Number": "00000002545",
      "Date": "2022-02-03T10:24:55",
      "АдресДоставки": "Ремонтна, 13",
      "Контрагент@navigationLinkUrl": "Document_ЗаказПокупателя(guid'abaa9b64-84ca-11ec-b3ce-00155dd72305')/Контрагент",
      "Контрагент": {
        "Description": "КОПЕРШЕ ПЕКАРНЯ ТОВ"
      },
      "DeletionMark": false,
      "Ответственный@navigationLinkUrl": "Document_ЗаказПокупателя(guid'abaa9b64-84ca-11ec-b3ce-00155dd72305')/Ответственный",
      "Ответственный": {
        "Code": "Шевцова Галина                                    "
      },
      "ДатаОтгрузки": "2022-02-07T00:00:00"
    },
    {
      "Ref_Key": "d5a56078-84cb-11ec-b3ce-00155dd72305",
      "Number": "00000002547",
      "Date": "2022-02-03T10:32:50",
      "АдресДоставки": "м. Київ, вул Лугова, 12",
      "Контрагент@navigationLinkUrl": "Document_ЗаказПокупателя(guid'd5a56078-84cb-11ec-b3ce-00155dd72305')/Контрагент",
      "Контрагент": {
        "Description": "АШАН УКРАЇНА ГІПЕРМАРКЕТ ТОВ"
      },
      "DeletionMark": false,
      "Ответственный@navigationLinkUrl": "Document_ЗаказПокупателя(guid'd5a56078-84cb-11ec-b3ce-00155dd72305')/Ответственный",
      "Ответственный": {
        "Code": "Крамаренко Леся                                   "
      },
      "ДатаОтгрузки": "2022-02-07T00:00:00"
    },
    {
      "Ref_Key": "214453ef-84ce-11ec-b3ce-00155dd72305",
      "Number": "00000002550",
      "Date": "2022-02-03T10:49:36",
      "АдресДоставки": "м.Київ, пр. Академіка Палладіна, 7-А",
      "Контрагент@navigationLinkUrl": "Document_ЗаказПокупателя(guid'214453ef-84ce-11ec-b3ce-00155dd72305')/Контрагент",
      "Контрагент": {
        "Description": "Новус Україна ТОВ"
      },
      "DeletionMark": false,
      "Ответственный@navigationLinkUrl": "Document_ЗаказПокупателя(guid'214453ef-84ce-11ec-b3ce-00155dd72305')/Ответственный",
      "Ответственный": {
        "Code": "Крамаренко Леся                                   "
      },
      "ДатаОтгрузки": "2022-02-07T00:00:00"
    },
    {
      "Ref_Key": "f4c6de85-84f3-11ec-b3ce-00155dd72305",
      "Number": "00000002611",
      "Date": "2022-02-03T15:19:57",
      "АдресДоставки": "м. Київ, пр-т Бандери, 21",
      "Контрагент@navigationLinkUrl": "Document_ЗаказПокупателя(guid'f4c6de85-84f3-11ec-b3ce-00155dd72305')/Контрагент",
      "Контрагент": {
        "Description": "Галя Балувана (Петрівка)"
      },
      "DeletionMark": false,
      "Ответственный@navigationLinkUrl": "Document_ЗаказПокупателя(guid'f4c6de85-84f3-11ec-b3ce-00155dd72305')/Ответственный",
      "Ответственный": {
        "Code": "Крамаренко Леся                                   "
      },
      "ДатаОтгрузки": "2022-02-07T00:00:00"
    },
    {
      "Ref_Key": "fec71b02-84ea-11ec-b3ce-00155dd72305",
      "Number": "00000002581",
      "Date": "2022-02-03T16:51:19",
      "АдресДоставки": "Києво - Святошинський р-н, с. Тарасівка, вул Київська, 1 Б",
      "Контрагент@navigationLinkUrl": "Document_ЗаказПокупателя(guid'fec71b02-84ea-11ec-b3ce-00155dd72305')/Контрагент",
      "Контрагент": {
        "Description": "АШАН УКРАЇНА ГІПЕРМАРКЕТ ТОВ"
      },
      "DeletionMark": false,
      "Ответственный@navigationLinkUrl": "Document_ЗаказПокупателя(guid'fec71b02-84ea-11ec-b3ce-00155dd72305')/Ответственный",
      "Ответственный": {
        "Code": "Крамаренко Леся                                   "
      },
      "ДатаОтгрузки": "2022-02-07T00:00:00"
    },
    {
      "Ref_Key": "20a6101f-858a-11ec-b3ce-00155dd72305",
      "Number": "00000002658",
      "Date": "2022-02-04T09:15:31",
      "АдресДоставки": "вул. Туманяна, 15-А",
      "Контрагент@navigationLinkUrl": "Document_ЗаказПокупателя(guid'20a6101f-858a-11ec-b3ce-00155dd72305')/Контрагент",
      "Контрагент": {
        "Description": "Кенді буфет(Бейкун Ю.О.)(новий)бн"
      },
      "DeletionMark": false,
      "Ответственный@navigationLinkUrl": "Document_ЗаказПокупателя(guid'20a6101f-858a-11ec-b3ce-00155dd72305')/Ответственный",
      "Ответственный": {
        "Code": "Балашова Лариса                                   "
      },
      "ДатаОтгрузки": "2022-02-07T00:00:00"
    },
    {
      "Ref_Key": "c78190c8-858a-11ec-b3ce-00155dd72305",
      "Number": "00000002659",
      "Date": "2022-02-04T09:19:33",
      "АдресДоставки": "м. Київ,  вул. Електріків , 29,А \" П'ятий елемент \"",
      "Контрагент@navigationLinkUrl": "Document_ЗаказПокупателя(guid'c78190c8-858a-11ec-b3ce-00155dd72305')/Контрагент",
      "Контрагент": {
        "Description": "Очеретня І.П. ФОП (5 елемент ) бн"
      },
      "DeletionMark": false,
      "Ответственный@navigationLinkUrl": "Document_ЗаказПокупателя(guid'c78190c8-858a-11ec-b3ce-00155dd72305')/Ответственный",
      "Ответственный": {
        "Code": "Наталія Рябченко                                  "
      },
      "ДатаОтгрузки": "2022-02-07T00:00:00"
    },
    {
      "Ref_Key": "eaff2de1-84ce-11ec-b3ce-00155dd72305",
      "Number": "00000002551",
      "Date": "2022-02-04T09:23:30",
      "АдресДоставки": "м. Київ, вул. Марка Вовчка, 21",
      "Контрагент@navigationLinkUrl": "Document_ЗаказПокупателя(guid'eaff2de1-84ce-11ec-b3ce-00155dd72305')/Контрагент",
      "Контрагент": {
        "Description": "Солодкий магазин(Подільська база) "
      },
      "DeletionMark": false,
      "Ответственный@navigationLinkUrl": "Document_ЗаказПокупателя(guid'eaff2de1-84ce-11ec-b3ce-00155dd72305')/Ответственный",
      "Ответственный": {
        "Code": "Балашова Лариса                                   "
      },
      "ДатаОтгрузки": "2022-02-07T00:00:00"
    }
  ]
}